{
  "updated_at": "2026-06-16T03:22:41.705016",
  "date": "2026-06-16",
  "total_records": 454,
  "best_sellers": [
    {
      "listing_id": "3da5898f-68f8-47de-4fd2-08dec090b44c",
      "title": "[bridger: Western] Unknown",
      "category": "Item",
      "seller": "MattDot",
      "qty_today": 120,
      "qty_yesterday": 26480,
      "units_sold": 26360
    },
    {
      "listing_id": "3da5898f-68f8-47de-4fd2-08dec090b44c",
      "title": "[Wizard Alchemy] Unknown",
      "category": "Item",
      "seller": "MattDot",
      "qty_today": 120,
      "qty_yesterday": 26480,
      "units_sold": 26360
    },
    {
      "listing_id": "3da5898f-68f8-47de-4fd2-08dec090b44c",
      "title": "[Welcome to Bloxburg] Unknown",
      "category": "Item",
      "seller": "MattDot",
      "qty_today": 120,
      "qty_yesterday": 26480,
      "units_sold": 26360
    },
    {
      "listing_id": "3da5898f-68f8-47de-4fd2-08dec090b44c",
      "title": "[War Tycoon] Unknown",
      "category": "Item",
      "seller": "MattDot",
      "qty_today": 120,
      "qty_yesterday": 26480,
      "units_sold": 26360
    },
    {
      "listing_id": "3da5898f-68f8-47de-4fd2-08dec090b44c",
      "title": "[Volleyball Legends] Unknown",
      "category": "Item",
      "seller": "MattDot",
      "qty_today": 120,
      "qty_yesterday": 26480,
      "units_sold": 26360
    },
    {
      "listing_id": "3da5898f-68f8-47de-4fd2-08dec090b44c",
      "title": "[Universal Tower Defense] Unknown",
      "category": "Item",
      "seller": "MattDot",
      "qty_today": 120,
      "qty_yesterday": 26480,
      "units_sold": 26360
    },
    {
      "listing_id": "3da5898f-68f8-47de-4fd2-08dec090b44c",
      "title": "[Toilet Tower Defense Gems] Unknown",
      "category": "Item",
      "seller": "MattDot",
      "qty_today": 120,
      "qty_yesterday": 26480,
      "units_sold": 26360
    },
    {
      "listing_id": "3da5898f-68f8-47de-4fd2-08dec090b44c",
      "title": "[The Forge] Unknown",
      "category": "Item",
      "seller": "MattDot",
      "qty_today": 120,
      "qty_yesterday": 26480,
      "units_sold": 26360
    },
    {
      "listing_id": "3da5898f-68f8-47de-4fd2-08dec090b44c",
      "title": "[Tap Simulator] Unknown",
      "category": "Item",
      "seller": "MattDot",
      "qty_today": 120,
      "qty_yesterday": 26480,
      "units_sold": 26360
    },
    {
      "listing_id": "3da5898f-68f8-47de-4fd2-08dec090b44c",
      "title": "[Tap Simulator Tokens] Unknown",
      "category": "Item",
      "seller": "MattDot",
      "qty_today": 120,
      "qty_yesterday": 26480,
      "units_sold": 26360
    },
    {
      "listing_id": "3da5898f-68f8-47de-4fd2-08dec090b44c",
      "title": "[TYPE://SOUL] Unknown",
      "category": "Item",
      "seller": "MattDot",
      "qty_today": 120,
      "qty_yesterday": 26480,
      "units_sold": 26360
    },
    {
      "listing_id": "3da5898f-68f8-47de-4fd2-08dec090b44c",
      "title": "[Swing Obby for Brainrots] Unknown",
      "category": "Item",
      "seller": "MattDot",
      "qty_today": 120,
      "qty_yesterday": 26480,
      "units_sold": 26360
    },
    {
      "listing_id": "3da5898f-68f8-47de-4fd2-08dec090b44c",
      "title": "[Survive Lava for Brainrots] Unknown",
      "category": "Item",
      "seller": "MattDot",
      "qty_today": 120,
      "qty_yesterday": 26480,
      "units_sold": 26360
    },
    {
      "listing_id": "3da5898f-68f8-47de-4fd2-08dec090b44c",
      "title": "[Summon Heroes] Unknown",
      "category": "Item",
      "seller": "MattDot",
      "qty_today": 120,
      "qty_yesterday": 26480,
      "units_sold": 26360
    },
    {
      "listing_id": "3da5898f-68f8-47de-4fd2-08dec090b44c",
      "title": "[Steal a Brainrot] Unknown",
      "category": "Item",
      "seller": "MattDot",
      "qty_today": 120,
      "qty_yesterday": 26480,
      "units_sold": 26360
    },
    {
      "listing_id": "3da5898f-68f8-47de-4fd2-08dec090b44c",
      "title": "[SpongeBob Tower Defense] Unknown",
      "category": "Item",
      "seller": "MattDot",
      "qty_today": 120,
      "qty_yesterday": 26480,
      "units_sold": 26360
    },
    {
      "listing_id": "3da5898f-68f8-47de-4fd2-08dec090b44c",
      "title": "[Spin a Baddie] Unknown",
      "category": "Item",
      "seller": "MattDot",
      "qty_today": 120,
      "qty_yesterday": 26480,
      "units_sold": 26360
    },
    {
      "listing_id": "3da5898f-68f8-47de-4fd2-08dec090b44c",
      "title": "[Sorcerer Tower Defense] Unknown",
      "category": "Item",
      "seller": "MattDot",
      "qty_today": 120,
      "qty_yesterday": 26480,
      "units_sold": 26360
    },
    {
      "listing_id": "3da5898f-68f8-47de-4fd2-08dec090b44c",
      "title": "[Sol's RNG] Unknown",
      "category": "Item",
      "seller": "MattDot",
      "qty_today": 120,
      "qty_yesterday": 26480,
      "units_sold": 26360
    },
    {
      "listing_id": "3da5898f-68f8-47de-4fd2-08dec090b44c",
      "title": "[Sniper Duels Gems] Unknown",
      "category": "Item",
      "seller": "MattDot",
      "qty_today": 120,
      "qty_yesterday": 26480,
      "units_sold": 26360
    },
    {
      "listing_id": "3da5898f-68f8-47de-4fd2-08dec090b44c",
      "title": "[Sniper Arena] Unknown",
      "category": "Item",
      "seller": "MattDot",
      "qty_today": 120,
      "qty_yesterday": 26480,
      "units_sold": 26360
    },
    {
      "listing_id": "3da5898f-68f8-47de-4fd2-08dec090b44c",
      "title": "[Slime RNG] Unknown",
      "category": "Item",
      "seller": "MattDot",
      "qty_today": 120,
      "qty_yesterday": 26480,
      "units_sold": 26360
    },
    {
      "listing_id": "3da5898f-68f8-47de-4fd2-08dec090b44c",
      "title": "[Sailor Piece] Unknown",
      "category": "Item",
      "seller": "MattDot",
      "qty_today": 120,
      "qty_yesterday": 26480,
      "units_sold": 26360
    },
    {
      "listing_id": "3da5898f-68f8-47de-4fd2-08dec090b44c",
      "title": "[Royale High Diamonds] Unknown",
      "category": "Item",
      "seller": "MattDot",
      "qty_today": 120,
      "qty_yesterday": 26480,
      "units_sold": 26360
    },
    {
      "listing_id": "3da5898f-68f8-47de-4fd2-08dec090b44c",
      "title": "[Roblox Top Ups] Unknown",
      "category": "Item",
      "seller": "MattDot",
      "qty_today": 120,
      "qty_yesterday": 26480,
      "units_sold": 26360
    },
    {
      "listing_id": "3da5898f-68f8-47de-4fd2-08dec090b44c",
      "title": "[Roblox Robux] Unknown",
      "category": "Item",
      "seller": "MattDot",
      "qty_today": 120,
      "qty_yesterday": 26480,
      "units_sold": 26360
    },
    {
      "listing_id": "3da5898f-68f8-47de-4fd2-08dec090b44c",
      "title": "[Roblox Limiteds] Unknown",
      "category": "Item",
      "seller": "MattDot",
      "qty_today": 120,
      "qty_yesterday": 26480,
      "units_sold": 26360
    },
    {
      "listing_id": "3da5898f-68f8-47de-4fd2-08dec090b44c",
      "title": "[Roblox Gift Cards] Unknown",
      "category": "Item",
      "seller": "MattDot",
      "qty_today": 120,
      "qty_yesterday": 26480,
      "units_sold": 26360
    },
    {
      "listing_id": "3da5898f-68f8-47de-4fd2-08dec090b44c",
      "title": "[Re:Rangers X] Unknown",
      "category": "Item",
      "seller": "MattDot",
      "qty_today": 120,
      "qty_yesterday": 26480,
      "units_sold": 26360
    },
    {
      "listing_id": "3da5898f-68f8-47de-4fd2-08dec090b44c",
      "title": "[Raise Animals] Unknown",
      "category": "Item",
      "seller": "MattDot",
      "qty_today": 120,
      "qty_yesterday": 26480,
      "units_sold": 26360
    },
    {
      "listing_id": "3da5898f-68f8-47de-4fd2-08dec090b44c",
      "title": "[Plants vs Brainrots] Unknown",
      "category": "Item",
      "seller": "MattDot",
      "qty_today": 120,
      "qty_yesterday": 26480,
      "units_sold": 26360
    },
    {
      "listing_id": "3da5898f-68f8-47de-4fd2-08dec090b44c",
      "title": "[Pets Go] Unknown",
      "category": "Item",
      "seller": "MattDot",
      "qty_today": 120,
      "qty_yesterday": 26480,
      "units_sold": 26360
    },
    {
      "listing_id": "3da5898f-68f8-47de-4fd2-08dec090b44c",
      "title": "[Pets Go Diamonds] Unknown",
      "category": "Item",
      "seller": "MattDot",
      "qty_today": 120,
      "qty_yesterday": 26480,
      "units_sold": 26360
    },
    {
      "listing_id": "3da5898f-68f8-47de-4fd2-08dec090b44c",
      "title": "[Pet Simulator 99] Unknown",
      "category": "Item",
      "seller": "MattDot",
      "qty_today": 120,
      "qty_yesterday": 26480,
      "units_sold": 26360
    },
    {
      "listing_id": "3da5898f-68f8-47de-4fd2-08dec090b44c",
      "title": "[Pet Simulator 99 Gems] Unknown",
      "category": "Item",
      "seller": "MattDot",
      "qty_today": 120,
      "qty_yesterday": 26480,
      "units_sold": 26360
    },
    {
      "listing_id": "3da5898f-68f8-47de-4fd2-08dec090b44c",
      "title": "[Noob Tower Defense] Unknown",
      "category": "Item",
      "seller": "MattDot",
      "qty_today": 120,
      "qty_yesterday": 26480,
      "units_sold": 26360
    },
    {
      "listing_id": "3da5898f-68f8-47de-4fd2-08dec090b44c",
      "title": "[Murderers VS Sheriffs DUELS] Unknown",
      "category": "Item",
      "seller": "MattDot",
      "qty_today": 120,
      "qty_yesterday": 26480,
      "units_sold": 26360
    },
    {
      "listing_id": "3da5898f-68f8-47de-4fd2-08dec090b44c",
      "title": "[Murder Mystery 2] Unknown",
      "category": "Item",
      "seller": "MattDot",
      "qty_today": 120,
      "qty_yesterday": 26480,
      "units_sold": 26360
    },
    {
      "listing_id": "3da5898f-68f8-47de-4fd2-08dec090b44c",
      "title": "[Mini War] Unknown",
      "category": "Item",
      "seller": "MattDot",
      "qty_today": 120,
      "qty_yesterday": 26480,
      "units_sold": 26360
    },
    {
      "listing_id": "3da5898f-68f8-47de-4fd2-08dec090b44c",
      "title": "[Knockout] Unknown",
      "category": "Item",
      "seller": "MattDot",
      "qty_today": 120,
      "qty_yesterday": 26480,
      "units_sold": 26360
    },
    {
      "listing_id": "3da5898f-68f8-47de-4fd2-08dec090b44c",
      "title": "[King Legacy] Unknown",
      "category": "Item",
      "seller": "MattDot",
      "qty_today": 120,
      "qty_yesterday": 26480,
      "units_sold": 26360
    },
    {
      "listing_id": "3da5898f-68f8-47de-4fd2-08dec090b44c",
      "title": "[Kick a Lucky Block] Unknown",
      "category": "Item",
      "seller": "MattDot",
      "qty_today": 120,
      "qty_yesterday": 26480,
      "units_sold": 26360
    },
    {
      "listing_id": "3da5898f-68f8-47de-4fd2-08dec090b44c",
      "title": "[KAIZEN] Unknown",
      "category": "Item",
      "seller": "MattDot",
      "qty_today": 120,
      "qty_yesterday": 26480,
      "units_sold": 26360
    },
    {
      "listing_id": "3da5898f-68f8-47de-4fd2-08dec090b44c",
      "title": "[Jujutsu Infinite] Unknown",
      "category": "Item",
      "seller": "MattDot",
      "qty_today": 120,
      "qty_yesterday": 26480,
      "units_sold": 26360
    },
    {
      "listing_id": "3da5898f-68f8-47de-4fd2-08dec090b44c",
      "title": "[Jailbreak] Unknown",
      "category": "Item",
      "seller": "MattDot",
      "qty_today": 120,
      "qty_yesterday": 26480,
      "units_sold": 26360
    },
    {
      "listing_id": "3da5898f-68f8-47de-4fd2-08dec090b44c",
      "title": "[Ink Game] Unknown",
      "category": "Item",
      "seller": "MattDot",
      "qty_today": 120,
      "qty_yesterday": 26480,
      "units_sold": 26360
    },
    {
      "listing_id": "3da5898f-68f8-47de-4fd2-08dec090b44c",
      "title": "[Hypershot] Unknown",
      "category": "Item",
      "seller": "MattDot",
      "qty_today": 120,
      "qty_yesterday": 26480,
      "units_sold": 26360
    },
    {
      "listing_id": "3da5898f-68f8-47de-4fd2-08dec090b44c",
      "title": "[Hunty Zombie] Unknown",
      "category": "Item",
      "seller": "MattDot",
      "qty_today": 120,
      "qty_yesterday": 26480,
      "units_sold": 26360
    },
    {
      "listing_id": "3da5898f-68f8-47de-4fd2-08dec090b44c",
      "title": "[Grow a Garden] Unknown",
      "category": "Item",
      "seller": "MattDot",
      "qty_today": 120,
      "qty_yesterday": 26480,
      "units_sold": 26360
    },
    {
      "listing_id": "3da5898f-68f8-47de-4fd2-08dec090b44c",
      "title": "[Grow a Garden Tokens] Unknown",
      "category": "Item",
      "seller": "MattDot",
      "qty_today": 120,
      "qty_yesterday": 26480,
      "units_sold": 26360
    }
  ]
}